autoriskml/__init__.py
autoriskml/api.py
autoriskml/binning/__init__.py
autoriskml/cleaning/__init__.py
autoriskml/connectors/__init__.py
autoriskml/core/__init__.py
autoriskml/deployment/__init__.py
autoriskml/explain/__init__.py
autoriskml/export/__init__.py
autoriskml/metrics/__init__.py
autoriskml/models/__init__.py
autoriskml/monitoring/__init__.py
autoriskml/profiling/__init__.py
autoriskml/scoring/__init__.py
autoriskml/utils/__init__.py
autoriskml-0.1.0.dist-info/licenses/LICENSE
autoriskml-0.1.0.dist-info/METADATA
autoriskml-0.1.0.dist-info/WHEEL
autoriskml-0.1.0.dist-info/entry_points.txt
autoriskml-0.1.0.dist-info/top_level.txt
autoriskml-0.1.0.dist-info/RECORD
