Metadata-Version: 2.4
Name: autoriskml
Version: 0.1.0
Summary: A Fully Automated Risk & Trading Intelligence Engine
Home-page: https://github.com/idrissbado/AutoRiskML
Author: Idriss Bado
Author-email: Idriss Bado <idrissbadoolivier@gmail.com>
License: MIT
Project-URL: Homepage, https://github.com/idrissbado/AutoRiskML
Project-URL: Documentation, https://github.com/idrissbado/AutoRiskML#readme
Project-URL: Repository, https://github.com/idrissbado/AutoRiskML
Project-URL: Bug Tracker, https://github.com/idrissbado/AutoRiskML/issues
Keywords: risk-management,machine-learning,credit-scoring,trading,fintech,psi,woe,iv,scorecard,drift-detection,mlops,automl,explainability
Classifier: Development Status :: 4 - Beta
Classifier: Intended Audience :: Financial and Insurance Industry
Classifier: License :: OSI Approved :: MIT License
Classifier: Programming Language :: Python :: 3
Classifier: Programming Language :: Python :: 3.8
Classifier: Programming Language :: Python :: 3.9
Classifier: Programming Language :: Python :: 3.10
Classifier: Programming Language :: Python :: 3.11
Requires-Python: >=3.8
License-File: LICENSE
Provides-Extra: perf
Requires-Dist: numpy>=1.20.0; extra == "perf"
Requires-Dist: numba>=0.55.0; extra == "perf"
Requires-Dist: pyarrow>=10.0.0; extra == "perf"
Provides-Extra: ml
Requires-Dist: scikit-learn>=1.0.0; extra == "ml"
Requires-Dist: xgboost>=1.7.0; extra == "ml"
Requires-Dist: lightgbm>=3.3.0; extra == "ml"
Provides-Extra: explain
Requires-Dist: shap>=0.41.0; extra == "explain"
Requires-Dist: lime>=0.2.0; extra == "explain"
Provides-Extra: distributed
Requires-Dist: dask[complete]>=2023.1.0; extra == "distributed"
Requires-Dist: ray>=2.0.0; extra == "distributed"
Provides-Extra: connectors
Requires-Dist: sqlalchemy>=2.0.0; extra == "connectors"
Requires-Dist: boto3>=1.26.0; extra == "connectors"
Requires-Dist: azure-storage-blob>=12.0.0; extra == "connectors"
Provides-Extra: azure
Requires-Dist: azureml-sdk>=1.50.0; extra == "azure"
Requires-Dist: azure-identity>=1.12.0; extra == "azure"
Provides-Extra: monitoring
Requires-Dist: prometheus-client>=0.16.0; extra == "monitoring"
Provides-Extra: reporting
Requires-Dist: matplotlib>=3.5.0; extra == "reporting"
Requires-Dist: seaborn>=0.12.0; extra == "reporting"
Requires-Dist: plotly>=5.10.0; extra == "reporting"
Provides-Extra: dev
Requires-Dist: pytest>=7.2.0; extra == "dev"
Requires-Dist: pytest-cov>=4.0.0; extra == "dev"
Requires-Dist: black>=23.0.0; extra == "dev"
Requires-Dist: mypy>=1.0.0; extra == "dev"
Provides-Extra: all
Requires-Dist: numpy>=1.20.0; extra == "all"
Requires-Dist: numba>=0.55.0; extra == "all"
Requires-Dist: pyarrow>=10.0.0; extra == "all"
Requires-Dist: scikit-learn>=1.0.0; extra == "all"
Requires-Dist: xgboost>=1.7.0; extra == "all"
Requires-Dist: lightgbm>=3.3.0; extra == "all"
Requires-Dist: shap>=0.41.0; extra == "all"
Requires-Dist: lime>=0.2.0; extra == "all"
Requires-Dist: matplotlib>=3.5.0; extra == "all"
Requires-Dist: plotly>=5.10.0; extra == "all"
Dynamic: author
Dynamic: home-page
Dynamic: license-file
Dynamic: requires-python
